src/__init__.py
bitecode-0.1.0.dist-info/METADATA
bitecode-0.1.0.dist-info/WHEEL
bitecode-0.1.0.dist-info/top_level.txt
bitecode-0.1.0.dist-info/RECORD
