Metadata-Version: 2.1
Name: bitecode
Version: 0.1.0
Summary: Bytecode Transformer
Home-page: UNKNOWN
License: MIT
Platform: UNKNOWN
Classifier: Programming Language :: Python :: 3
Classifier: License :: OSI Approved :: MIT License
Classifier: Operating System :: OS Independent
Requires-Python: >=3.6
